{
  "info": {
    "size": {
      "X": 31,
      "Y": 14
    },
    "min": {
      "X": -14,
      "Y": -6
    },
    "area": 401
  },
  "cells": [
    {
      "element": "SedimentaryRock",
      "mass": 1840,
      "temperature": 250.149994,
      "location_x": -10,
      "location_y": -6
    },
    {
      "element": "SedimentaryRock",
      "mass": 1840,
      "temperature": 250.149994,
      "location_x": -9,
      "location_y": -6
    },
    {
      "element": "SedimentaryRock",
      "mass": 1840,
      "temperature": 250.149994,
      "location_x": -8,
      "location_y": -6
    },
    {
      "element": "SedimentaryRock",
      "mass": 1840,
      "temperature": 250.149994,
      "location_x": -6,
      "location_y": -6
    },
    {
      "element": "SedimentaryRock",
      "mass": 1840,
      "temperature": 250.149994,
      "location_x": -5,
      "location_y": -6
    },
    {
      "element": "Ice",
      "mass": 1059.43005,
      "temperature": 251.149994,
      "location_x": -4,
      "location_y": -6
    },
    {
      "element": "Ice",
      "mass": 1059.43005,
      "temperature": 251.149994,
      "location_x": -3,
      "location_y": -6
    },
    {
      "element": "Ice",
      "mass": 1059.43005,
      "temperature": 251.149994,
      "location_x": -2,
      "location_y": -6
    },
    {
      "element": "Ice",
      "mass": 1059.43005,
      "temperature": 251.149994,
      "location_x": -1,
      "location_y": -6
    },
    {
      "element": "Ice",
      "mass": 1059.43005,
      "temperature": 251.149994,
      "location_y": -6
    },
    {
      "element": "Dirt",
      "mass": 1840,
      "temperature": 258.149994,
      "location_x": 1,
      "location_y": -6
    },
    {
      "element": "SedimentaryRock",
      "mass": 1840,
      "temperature": 250.149994,
      "location_x": 2,
      "location_y": -6
    },
    {
      "element": "SedimentaryRock",
      "mass": 1840,
      "temperature": 250.149994,
      "location_x": 3,
      "location_y": -6
    },
    {
      "element": "Dirt",
      "mass": 1840,
      "temperature": 258.149994,
      "location_x": 4,
      "location_y": -6
    },
    {
      "element": "SedimentaryRock",
      "mass": 1840,
      "temperature": 250.149994,
      "location_x": 5,
      "location_y": -6
    },
    {
      "element": "SedimentaryRock",
      "mass": 1840,
      "temperature": 250.149994,
      "location_x": 6,
      "location_y": -6
    },
    {
      "element": "Dirt",
      "mass": 1840,
      "temperature": 258.149994,
      "location_x": 7,
      "location_y": -6
    },
    {
      "element": "Wolframite",
      "mass": 575.950012,
      "temperature": 232.596725,
      "location_x": 8,
      "location_y": -6
    },
    {
      "element": "Wolframite",
      "mass": 575.950012,
      "temperature": 232.319412,
      "location_x": 9,
      "location_y": -6
    },
    {
      "element": "Dirt",
      "mass": 1840,
      "temperature": 258.149994,
      "location_x": 10,
      "location_y": -6
    },
    {
      "element": "SedimentaryRock",
      "mass": 1840,
      "temperature": 250.149994,
      "location_x": 11,
      "location_y": -6
    },
    {
      "element": "SedimentaryRock",
      "mass": 1840,
      "temperature": 262.428131,
      "location_x": -12,
      "location_y": -5
    },
    {
      "element": "Ice",
      "mass": 980,
      "temperature": 263.212769,
      "location_x": -11,
      "location_y": -5
    },
    {
      "element": "Ice",
      "mass": 980,
      "temperature": 262.971649,
      "location_x": -10,
      "location_y": -5
    },
    {
      "element": "Ice",
      "mass": 980,
      "temperature": 261.128632,
      "location_x": -9,
      "location_y": -5
    },
    {
      "element": "Ice",
      "mass": 980,
      "temperature": 259.431427,
      "location_x": -8,
      "location_y": -5
    },
    {
      "element": "Ice",
      "mass": 980,
      "temperature": 254.372925,
      "location_x": -7,
      "location_y": -5
    },
    {
      "element": "Dirt",
      "mass": 1840,
      "temperature": 258.149994,
      "location_x": -6,
      "location_y": -5
    },
    {
      "element": "Ice",
      "mass": 1059.43005,
      "temperature": 251.149994,
      "location_x": -5,
      "location_y": -5
    },
    {
      "element": "Ice",
      "mass": 1059.43005,
      "temperature": 251.149994,
      "location_x": -4,
      "location_y": -5
    },
    {
      "element": "Snow",
      "mass": 10,
      "temperature": 261.149994,
      "location_x": -3,
      "location_y": -5
    },
    {
      "element": "Snow",
      "mass": 10,
      "temperature": 259.149994,
      "location_x": -2,
      "location_y": -5
    },
    {
      "element": "Dirt",
      "mass": 1840,
      "temperature": 258.149994,
      "location_x": -1,
      "location_y": -5
    },
    {
      "element": "Dirt",
      "mass": 1840,
      "temperature": 258.149994,
      "location_y": -5
    },
    {
      "element": "Dirt",
      "mass": 1840,
      "temperature": 258.149994,
      "location_x": 1,
      "location_y": -5
    },
    {
      "element": "SedimentaryRock",
      "mass": 1840,
      "temperature": 250.149994,
      "location_x": 2,
      "location_y": -5
    },
    {
      "element": "Dirt",
      "mass": 1840,
      "temperature": 258.149994,
      "location_x": 3,
      "location_y": -5
    },
    {
      "element": "Snow",
      "mass": 30,
      "temperature": 261.149994,
      "location_x": 4,
      "location_y": -5
    },
    {
      "element": "Snow",
      "mass": 30,
      "temperature": 261.149994,
      "location_x": 5,
      "location_y": -5
    },
    {
      "element": "Snow",
      "mass": 30,
      "temperature": 261.149994,
      "location_x": 6,
      "location_y": -5
    },
    {
      "element": "Dirt",
      "mass": 1840,
      "temperature": 258.149994,
      "location_x": 7,
      "location_y": -5
    },
    {
      "element": "Dirt",
      "mass": 1840,
      "temperature": 258.149994,
      "location_x": 8,
      "location_y": -5
    },
    {
      "element": "Wolframite",
      "mass": 575.950012,
      "temperature": 233.505692,
      "location_x": 9,
      "location_y": -5
    },
    {
      "element": "Wolframite",
      "mass": 575.950012,
      "temperature": 233.702026,
      "location_x": 10,
      "location_y": -5
    },
    {
      "element": "Dirt",
      "mass": 1840,
      "temperature": 258.149994,
      "location_x": 11,
      "location_y": -5
    },
    {
      "element": "SedimentaryRock",
      "mass": 1840,
      "temperature": 250.149994,
      "location_x": 12,
      "location_y": -5
    },
    {
      "element": "SedimentaryRock",
      "mass": 1840,
      "temperature": 250.149994,
      "location_x": 13,
      "location_y": -5
    },
    {
      "element": "SedimentaryRock",
      "mass": 1840,
      "temperature": 250.149994,
      "location_x": 14,
      "location_y": -5
    },
    {
      "element": "SandStone",
      "mass": 100,
      "temperature": 264.981323,
      "location_x": -13,
      "location_y": -4
    },
    {
      "element": "SandStone",
      "mass": 100,
      "temperature": 265.137115,
      "location_x": -12,
      "location_y": -4
    },
    {
      "element": "Snow",
      "mass": 1,
      "temperature": 264.332672,
      "location_x": -11,
      "location_y": -4
    },
    {
      "element": "SandStone",
      "mass": 100,
      "temperature": 265.120697,
      "location_x": -10,
      "location_y": -4
    },
    {
      "element": "Snow",
      "mass": 10,
      "temperature": 264.008362,
      "location_x": -9,
      "location_y": -4
    },
    {
      "element": "SandStone",
      "mass": 100,
      "temperature": 265.07782,
      "location_x": -8,
      "location_y": -4
    },
    {
      "element": "Dirt",
      "mass": 1840,
      "temperature": 258.149994,
      "location_x": -7,
      "location_y": -4
    },
    {
      "element": "SandStone",
      "mass": 100,
      "temperature": 265.120911,
      "location_x": -6,
      "location_y": -4
    },
    {
      "element": "SandStone",
      "mass": 100,
      "temperature": 265.127014,
      "location_x": -5,
      "location_y": -4
    },
    {
      "element": "SandStone",
      "mass": 100,
      "temperature": 265.111664,
      "location_x": -4,
      "location_y": -4
    },
    {
      "element": "SandStone",
      "mass": 100,
      "temperature": 265.130432,
      "location_x": -3,
      "location_y": -4
    },
    {
      "element": "SandStone",
      "mass": 100,
      "temperature": 265.128906,
      "location_x": -2,
      "location_y": -4
    },
    {
      "element": "SandStone",
      "mass": 100,
      "temperature": 265.107025,
      "location_x": -1,
      "location_y": -4
    },
    {
      "element": "SandStone",
      "mass": 100,
      "temperature": 265.13327,
      "location_y": -4
    },
    {
      "element": "SandStone",
      "mass": 100,
      "temperature": 265.130859,
      "location_x": 1,
      "location_y": -4
    },
    {
      "element": "SandStone",
      "mass": 100,
      "temperature": 265.162933,
      "location_x": 2,
      "location_y": -4
    },
    {
      "element": "SandStone",
      "mass": 100,
      "temperature": 265.136322,
      "location_x": 3,
      "location_y": -4
    },
    {
      "element": "SandStone",
      "mass": 100,
      "temperature": 265.1362,
      "location_x": 4,
      "location_y": -4
    },
    {
      "element": "SandStone",
      "mass": 100,
      "temperature": 265.135529,
      "location_x": 5,
      "location_y": -4
    },
    {
      "element": "SandStone",
      "mass": 100,
      "temperature": 265.136841,
      "location_x": 6,
      "location_y": -4
    },
    {
      "element": "SandStone",
      "mass": 100,
      "temperature": 265.133331,
      "location_x": 7,
      "location_y": -4
    },
    {
      "element": "SandStone",
      "mass": 100,
      "temperature": 265.069916,
      "location_x": 8,
      "location_y": -4
    },
    {
      "element": "SandStone",
      "mass": 100,
      "temperature": 264.621521,
      "location_x": 9,
      "location_y": -4
    },
    {
      "element": "SandStone",
      "mass": 100,
      "temperature": 264.623383,
      "location_x": 10,
      "location_y": -4
    },
    {
      "element": "SandStone",
      "mass": 100,
      "temperature": 265.100983,
      "location_x": 11,
      "location_y": -4
    },
    {
      "element": "SandStone",
      "mass": 100,
      "temperature": 265.128082,
      "location_x": 12,
      "location_y": -4
    },
    {
      "element": "SandStone",
      "mass": 100,
      "temperature": 265.124054,
      "location_x": 13,
      "location_y": -4
    },
    {
      "element": "SedimentaryRock",
      "mass": 1840,
      "temperature": 250.149994,
      "location_x": 14,
      "location_y": -4
    },
    {
      "element": "SedimentaryRock",
      "mass": 1840,
      "temperature": 250.149994,
      "location_x": 15,
      "location_y": -4
    },
    {
      "element": "SedimentaryRock",
      "mass": 1840,
      "temperature": 250.149994,
      "location_x": 16,
      "location_y": -4
    },
    {
      "element": "Oxygen",
      "mass": 0.750870883,
      "temperature": 262.466339,
      "location_x": -13,
      "location_y": -3
    },
    {
      "element": "Oxygen",
      "mass": 0.897377372,
      "temperature": 264.300507,
      "location_x": -12,
      "location_y": -3
    },
    {
      "element": "Oxygen",
      "mass": 0.925182581,
      "temperature": 264.94693,
      "location_x": -11,
      "location_y": -3
    },
    {
      "element": "Snow",
      "mass": 10,
      "temperature": 265.147949,
      "location_x": -10,
      "location_y": -3
    },
    {
      "element": "Snow",
      "mass": 10,
      "temperature": 264.946716,
      "location_x": -9,
      "location_y": -3
    },
    {
      "element": "Oxygen",
      "mass": 1.02315426,
      "temperature": 265.134491,
      "location_x": -8,
      "location_y": -3
    },
    {
      "element": "Oxygen",
      "mass": 1.01822746,
      "temperature": 264.181458,
      "location_x": -7,
      "location_y": -3
    },
    {
      "element": "Oxygen",
      "mass": 1.00782967,
      "temperature": 265.14679,
      "location_x": -6,
      "location_y": -3
    },
    {
      "element": "Oxygen",
      "mass": 0.986457944,
      "temperature": 265.150452,
      "location_x": -5,
      "location_y": -3
    },
    {
      "element": "Oxygen",
      "mass": 0.95612669,
      "temperature": 265.150299,
      "location_x": -4,
      "location_y": -3
    },
    {
      "element": "Oxygen",
      "mass": 0.917639017,
      "temperature": 265.149933,
      "location_x": -3,
      "location_y": -3
    },
    {
      "element": "Oxygen",
      "mass": 0.855107486,
      "temperature": 265.149963,
      "location_x": -2,
      "location_y": -3
    },
    {
      "element": "Oxygen",
      "mass": 0.793704391,
      "temperature": 265.385834,
      "location_x": -1,
      "location_y": -3
    },
    {
      "element": "Oxygen",
      "mass": 0.774937272,
      "temperature": 265.318878,
      "location_y": -3
    },
    {
      "element": "Oxygen",
      "mass": 0.796835244,
      "temperature": 265.55188,
      "location_x": 1,
      "location_y": -3
    },
    {
      "element": "Oxygen",
      "mass": 0.853174865,
      "temperature": 266.176605,
      "location_x": 2,
      "location_y": -3
    },
    {
      "element": "Oxygen",
      "mass": 0.92483896,
      "temperature": 265.179199,
      "location_x": 3,
      "location_y": -3
    },
    {
      "element": "Oxygen",
      "mass": 1.02826583,
      "temperature": 265.16153,
      "location_x": 4,
      "location_y": -3
    },
    {
      "element": "Oxygen",
      "mass": 0.98907423,
      "temperature": 265.170013,
      "location_x": 5,
      "location_y": -3
    },
    {
      "element": "Oxygen",
      "mass": 1.03569603,
      "temperature": 265.154144,
      "location_x": 6,
      "location_y": -3
    },
    {
      "element": "Oxygen",
      "mass": 1.02905905,
      "temperature": 265.668274,
      "location_x": 7,
      "location_y": -3
    },
    {
      "element": "Oxygen",
      "mass": 0.998679817,
      "temperature": 265.150055,
      "location_x": 8,
      "location_y": -3
    },
    {
      "element": "Oxygen",
      "mass": 1.01640677,
      "temperature": 265.155365,
      "location_x": 9,
      "location_y": -3
    },
    {
      "element": "Oxygen",
      "mass": 0.983513415,
      "temperature": 265.145081,
      "location_x": 10,
      "location_y": -3
    },
    {
      "element": "Oxygen",
      "mass": 0.972352266,
      "temperature": 264.936584,
      "location_x": 11,
      "location_y": -3
    },
    {
      "element": "Oxygen",
      "mass": 0.966645896,
      "temperature": 265.148315,
      "location_x": 12,
      "location_y": -3
    },
    {
      "element": "Oxygen",
      "mass": 0.970272362,
      "temperature": 265.135468,
      "location_x": 13,
      "location_y": -3
    },
    {
      "element": "Oxygen",
      "mass": 0.978935897,
      "temperature": 264.898712,
      "location_x": 14,
      "location_y": -3
    },
    {
      "element": "Oxygen",
      "mass": 0.984861016,
      "temperature": 263.755676,
      "location_x": 15,
      "location_y": -3
    },
    {
      "element": "SedimentaryRock",
      "mass": 1840,
      "temperature": 250.149994,
      "location_x": 16,
      "location_y": -3
    },
    {
      "element": "Oxygen",
      "mass": 0.780526936,
      "temperature": 250.022827,
      "location_x": -13,
      "location_y": -2
    },
    {
      "element": "Oxygen",
      "mass": 0.875444472,
      "temperature": 264.93927,
      "location_x": -12,
      "location_y": -2
    },
    {
      "element": "Oxygen",
      "mass": 0.898540854,
      "temperature": 264.289734,
      "location_x": -11,
      "location_y": -2
    },
    {
      "element": "Oxygen",
      "mass": 0.890799999,
      "temperature": 265.142639,
      "location_x": -10,
      "location_y": -2
    },
    {
      "element": "Snow",
      "mass": 10,
      "temperature": 265.147949,
      "location_x": -9,
      "location_y": -2
    },
    {
      "element": "Oxygen",
      "mass": 1.02498233,
      "temperature": 265.14975,
      "location_x": -8,
      "location_y": -2
    },
    {
      "element": "Oxygen",
      "mass": 1.01906681,
      "temperature": 265.612366,
      "location_x": -7,
      "location_y": -2
    },
    {
      "element": "Oxygen",
      "mass": 1.00806129,
      "temperature": 265.148804,
      "location_x": -6,
      "location_y": -2
    },
    {
      "element": "Oxygen",
      "mass": 0.985395133,
      "temperature": 265.152435,
      "location_x": -5,
      "location_y": -2
    },
    {
      "element": "Oxygen",
      "mass": 0.957414806,
      "temperature": 265.150024,
      "location_x": -4,
      "location_y": -2
    },
    {
      "element": "Oxygen",
      "mass": 0.92274648,
      "temperature": 265.148987,
      "location_x": -3,
      "location_y": -2
    },
    {
      "element": "Oxygen",
      "mass": 0.832927823,
      "temperature": 265.16333,
      "location_x": -2,
      "location_y": -2
    },
    {
      "element": "Oxygen",
      "mass": 0.871509612,
      "temperature": 265.150146,
      "location_x": -1,
      "location_y": -2
    },
    {
      "element": "Oxygen",
      "mass": 0.835793078,
      "temperature": 265.508514,
      "location_y": -2
    },
    {
      "element": "Oxygen",
      "mass": 0.881363869,
      "temperature": 265.547668,
      "location_x": 1,
      "location_y": -2
    },
    {
      "element": "Oxygen",
      "mass": 0.939473212,
      "temperature": 265.440338,
      "location_x": 2,
      "location_y": -2
    },
    {
      "element": "Oxygen",
      "mass": 0.821528077,
      "temperature": 265.310028,
      "location_x": 3,
      "location_y": -2
    },
    {
      "element": "Oxygen",
      "mass": 0.995716333,
      "temperature": 265.84787,
      "location_x": 4,
      "location_y": -2
    },
    {
      "element": "Oxygen",
      "mass": 1.03151894,
      "temperature": 265.172516,
      "location_x": 5,
      "location_y": -2
    },
    {
      "element": "Oxygen",
      "mass": 1.03965008,
      "temperature": 265.599243,
      "location_x": 6,
      "location_y": -2
    },
    {
      "element": "Oxygen",
      "mass": 1.03066325,
      "temperature": 265.157318,
      "location_x": 7,
      "location_y": -2
    },
    {
      "element": "Oxygen",
      "mass": 1.00972736,
      "temperature": 265.157501,
      "location_x": 8,
      "location_y": -2
    },
    {
      "element": "Oxygen",
      "mass": 0.990342319,
      "temperature": 265.14978,
      "location_x": 9,
      "location_y": -2
    },
    {
      "element": "Oxygen",
      "mass": 0.9690606,
      "temperature": 265.149963,
      "location_x": 10,
      "location_y": -2
    },
    {
      "element": "Oxygen",
      "mass": 0.956291735,
      "temperature": 265.148621,
      "location_x": 11,
      "location_y": -2
    },
    {
      "element": "Oxygen",
      "mass": 0.95101124,
      "temperature": 265.143646,
      "location_x": 12,
      "location_y": -2
    },
    {
      "element": "Oxygen",
      "mass": 0.952847838,
      "temperature": 265.067841,
      "location_x": 13,
      "location_y": -2
    },
    {
      "element": "Oxygen",
      "mass": 0.9826895,
      "temperature": 260.970215,
      "location_x": 14,
      "location_y": -2
    },
    {
      "element": "Oxygen",
      "mass": 0.969201326,
      "temperature": 262.613434,
      "location_x": 15,
      "location_y": -2
    },
    {
      "element": "Ice",
      "mass": 980,
      "temperature": 254.149994,
      "location_x": 16,
      "location_y": -2
    },
    {
      "element": "Oxygen",
      "mass": 0.80777055,
      "temperature": 262.209869,
      "location_x": -13,
      "location_y": -1
    },
    {
      "element": "Oxygen",
      "mass": 0.871320248,
      "temperature": 265.070282,
      "location_x": -12,
      "location_y": -1
    },
    {
      "element": "Oxygen",
      "mass": 0.887323976,
      "temperature": 265.136414,
      "location_x": -11,
      "location_y": -1
    },
    {
      "element": "Oxygen",
      "mass": 0.887741268,
      "temperature": 265.144684,
      "location_x": -10,
      "location_y": -1
    },
    {
      "element": "Snow",
      "mass": 10,
      "temperature": 265.147949,
      "location_x": -9,
      "location_y": -1
    },
    {
      "element": "Oxygen",
      "mass": 1.03015113,
      "temperature": 265.149994,
      "location_x": -8,
      "location_y": -1
    },
    {
      "element": "Oxygen",
      "mass": 1.02219343,
      "temperature": 265.149994,
      "location_x": -7,
      "location_y": -1
    },
    {
      "element": "Oxygen",
      "mass": 1.00602484,
      "temperature": 265.150238,
      "location_x": -6,
      "location_y": -1
    },
    {
      "element": "Oxygen",
      "mass": 0.986528158,
      "temperature": 265.151428,
      "location_x": -5,
      "location_y": -1
    },
    {
      "element": "Oxygen",
      "mass": 0.966938317,
      "temperature": 265.151428,
      "location_x": -4,
      "location_y": -1
    },
    {
      "element": "Oxygen",
      "mass": 0.941125929,
      "temperature": 265.151215,
      "location_x": -3,
      "location_y": -1
    },
    {
      "element": "Oxygen",
      "mass": 0.911363184,
      "temperature": 265.242889,
      "location_x": -2,
      "location_y": -1
    },
    {
      "element": "Oxygen",
      "mass": 0.895528316,
      "temperature": 265.160156,
      "location_x": -1,
      "location_y": -1
    },
    {
      "element": "Oxygen",
      "mass": 0.88525635,
      "temperature": 266.33606,
      "location_y": -1
    },
    {
      "element": "Oxygen",
      "mass": 0.894558787,
      "temperature": 268.874939,
      "location_x": 1,
      "location_y": -1
    },
    {
      "element": "Oxygen",
      "mass": 0.926288128,
      "temperature": 269.040771,
      "location_x": 2,
      "location_y": -1
    },
    {
      "element": "Oxygen",
      "mass": 0.968493342,
      "temperature": 267.46698,
      "location_x": 3,
      "location_y": -1
    },
    {
      "element": "Oxygen",
      "mass": 1.00864065,
      "temperature": 266.008026,
      "location_x": 4,
      "location_y": -1
    },
    {
      "element": "Oxygen",
      "mass": 1.04543304,
      "temperature": 265.628906,
      "location_x": 5,
      "location_y": -1
    },
    {
      "element": "Oxygen",
      "mass": 1.04839921,
      "temperature": 265.152527,
      "location_x": 6,
      "location_y": -1
    },
    {
      "element": "Oxygen",
      "mass": 1.01615298,
      "temperature": 265.154999,
      "location_x": 7,
      "location_y": -1
    },
    {
      "element": "Oxygen",
      "mass": 0.989338696,
      "temperature": 265.154694,
      "location_x": 8,
      "location_y": -1
    },
    {
      "element": "Oxygen",
      "mass": 0.969568372,
      "temperature": 265.150085,
      "location_x": 9,
      "location_y": -1
    },
    {
      "element": "Oxygen",
      "mass": 0.948351264,
      "temperature": 265.149933,
      "location_x": 10,
      "location_y": -1
    },
    {
      "element": "Oxygen",
      "mass": 0.930719614,
      "temperature": 265.149994,
      "location_x": 11,
      "location_y": -1
    },
    {
      "element": "Oxygen",
      "mass": 0.910597444,
      "temperature": 265.148804,
      "location_x": 12,
      "location_y": -1
    },
    {
      "element": "Oxygen",
      "mass": 0.91274184,
      "temperature": 265.084351,
      "location_x": 13,
      "location_y": -1
    },
    {
      "element": "Oxygen",
      "mass": 0.961302578,
      "temperature": 263.988831,
      "location_x": 14,
      "location_y": -1
    },
    {
      "element": "Ice",
      "mass": 980,
      "temperature": 254.149994,
      "location_x": 15,
      "location_y": -1
    },
    {
      "element": "Ice",
      "mass": 980,
      "temperature": 254.149994,
      "location_x": 16,
      "location_y": -1
    },
    {
      "element": "Oxygen",
      "mass": 0.614111066,
      "temperature": 254.186935,
      "location_x": -13
    },
    {
      "element": "Oxygen",
      "mass": 0.886079013,
      "temperature": 264.047089,
      "location_x": -12
    },
    {
      "element": "Oxygen",
      "mass": 0.906044185,
      "temperature": 264.901062,
      "location_x": -11
    },
    {
      "element": "Oxygen",
      "mass": 0.912744999,
      "temperature": 265.110077,
      "location_x": -10
    },
    {
      "element": "SandStone",
      "mass": 100,
      "temperature": 265.149994,
      "location_x": -9
    },
    {
      "element": "SandStone",
      "mass": 100,
      "temperature": 264.637512,
      "location_x": -8
    },
    {
      "element": "SandStone",
      "mass": 100,
      "temperature": 265.149994,
      "location_x": -7
    },
    {
      "element": "Oxygen",
      "mass": 0.999771655,
      "temperature": 265.283112,
      "location_x": -6
    },
    {
      "element": "Oxygen",
      "mass": 0.990064859,
      "temperature": 265.420349,
      "location_x": -5
    },
    {
      "element": "Oxygen",
      "mass": 0.977404833,
      "temperature": 265.152527,
      "location_x": -4
    },
    {
      "element": "Oxygen",
      "mass": 0.96347183,
      "temperature": 265.285004,
      "location_x": -3
    },
    {
      "element": "Oxygen",
      "mass": 0.957312882,
      "temperature": 265.230988,
      "location_x": -2
    },
    {
      "element": "Oxygen",
      "mass": 0.955423117,
      "temperature": 265.477112,
      "location_x": -1
    },
    {
      "element": "Oxygen",
      "mass": 0.968404412,
      "temperature": 269.40509
    },
    {
      "element": "Oxygen",
      "mass": 0.994079232,
      "temperature": 283.919586,
      "location_x": 1
    },
    {
      "element": "Oxygen",
      "mass": 1.02345133,
      "temperature": 296.293732,
      "location_x": 2
    },
    {
      "element": "Oxygen",
      "mass": 1.04672337,
      "temperature": 282.91806,
      "location_x": 3
    },
    {
      "element": "SandStone",
      "mass": 100,
      "temperature": 265.218201,
      "location_x": 4
    },
    {
      "element": "SandStone",
      "mass": 100,
      "temperature": 265.149994,
      "location_x": 5
    },
    {
      "element": "SandStone",
      "mass": 100,
      "temperature": 265.149994,
      "location_x": 6
    },
    {
      "element": "Oxygen",
      "mass": 0.974235833,
      "temperature": 265.150146,
      "location_x": 7
    },
    {
      "element": "Oxygen",
      "mass": 0.954960585,
      "temperature": 265.149994,
      "location_x": 8
    },
    {
      "element": "Oxygen",
      "mass": 0.96482271,
      "temperature": 265.149994,
      "location_x": 9
    },
    {
      "element": "Oxygen",
      "mass": 0.934691012,
      "temperature": 265.150024,
      "location_x": 10
    },
    {
      "element": "Oxygen",
      "mass": 0.899399042,
      "temperature": 265.149963,
      "location_x": 11
    },
    {
      "element": "Oxygen",
      "mass": 0.858396113,
      "temperature": 265.14917,
      "location_x": 12
    },
    {
      "element": "Oxygen",
      "mass": 0.830334246,
      "temperature": 265.148376,
      "location_x": 13
    },
    {
      "element": "SandStone",
      "mass": 100,
      "temperature": 265.135956,
      "location_x": 14
    },
    {
      "element": "Ice",
      "mass": 980,
      "temperature": 254.149994,
      "location_x": 15
    },
    {
      "element": "Oxygen",
      "mass": 0.870268047,
      "temperature": 264.077545,
      "location_x": -13,
      "location_y": 1
    },
    {
      "element": "Oxygen",
      "mass": 0.925118029,
      "temperature": 264.973969,
      "location_x": -12,
      "location_y": 1
    },
    {
      "element": "Oxygen",
      "mass": 0.952166259,
      "temperature": 261.492371,
      "location_x": -11,
      "location_y": 1
    },
    {
      "element": "Oxygen",
      "mass": 0.974666476,
      "temperature": 265.083771,
      "location_x": -10,
      "location_y": 1
    },
    {
      "element": "SandStone",
      "mass": 100,
      "temperature": 264.637756,
      "location_x": -9,
      "location_y": 1
    },
    {
      "element": "Wolframite",
      "mass": 575.950012,
      "temperature": 235.447403,
      "location_x": -8,
      "location_y": 1
    },
    {
      "element": "SandStone",
      "mass": 100,
      "temperature": 264.637756,
      "location_x": -7,
      "location_y": 1
    },
    {
      "element": "Oxygen",
      "mass": 1.00271344,
      "temperature": 265.149994,
      "location_x": -6,
      "location_y": 1
    },
    {
      "element": "Oxygen",
      "mass": 0.991029441,
      "temperature": 265.150146,
      "location_x": -5,
      "location_y": 1
    },
    {
      "element": "Oxygen",
      "mass": 0.985207617,
      "temperature": 265.150696,
      "location_x": -4,
      "location_y": 1
    },
    {
      "element": "Oxygen",
      "mass": 0.985663116,
      "temperature": 265.231262,
      "location_x": -3,
      "location_y": 1
    },
    {
      "element": "Oxygen",
      "mass": 0.990932465,
      "temperature": 265.243408,
      "location_x": -2,
      "location_y": 1
    },
    {
      "element": "Oxygen",
      "mass": 1.01315761,
      "temperature": 270.296661,
      "location_x": -1,
      "location_y": 1
    },
    {
      "element": "Oxygen",
      "mass": 1.0639025,
      "temperature": 297.862854,
      "location_y": 1
    },
    {
      "element": "Oxygen",
      "mass": 1.1876806,
      "temperature": 285.918976,
      "location_x": 1,
      "location_y": 1
    },
    {
      "element": "OxyRock",
      "mass": 198.399963,
      "temperature": 299.353485,
      "location_x": 2,
      "location_y": 1
    },
    {
      "element": "OxyRock",
      "mass": 198.879974,
      "temperature": 297.696106,
      "location_x": 3,
      "location_y": 1
    },
    {
      "element": "SandStone",
      "mass": 100,
      "temperature": 265.469818,
      "location_x": 4,
      "location_y": 1
    },
    {
      "element": "Snow",
      "mass": 10,
      "temperature": 259.149994,
      "location_x": 5,
      "location_y": 1
    },
    {
      "element": "SandStone",
      "mass": 100,
      "temperature": 265.149994,
      "location_x": 6,
      "location_y": 1
    },
    {
      "element": "Oxygen",
      "mass": 0.961253345,
      "temperature": 265.150085,
      "location_x": 7,
      "location_y": 1
    },
    {
      "element": "Oxygen",
      "mass": 0.947896123,
      "temperature": 265.149994,
      "location_x": 8,
      "location_y": 1
    },
    {
      "element": "Oxygen",
      "mass": 0.930675268,
      "temperature": 265.149994,
      "location_x": 9,
      "location_y": 1
    },
    {
      "element": "Oxygen",
      "mass": 0.955854237,
      "temperature": 265.149994,
      "location_x": 10,
      "location_y": 1
    },
    {
      "element": "Oxygen",
      "mass": 0.882152438,
      "temperature": 265.149994,
      "location_x": 11,
      "location_y": 1
    },
    {
      "element": "Oxygen",
      "mass": 0.812465489,
      "temperature": 265.149994,
      "location_x": 12,
      "location_y": 1
    },
    {
      "element": "Oxygen",
      "mass": 0.78502357,
      "temperature": 265.149902,
      "location_x": 13,
      "location_y": 1
    },
    {
      "element": "SandStone",
      "mass": 100,
      "temperature": 265.142853,
      "location_x": 14,
      "location_y": 1
    },
    {
      "element": "SandStone",
      "mass": 100,
      "temperature": 264.931763,
      "location_x": -14,
      "location_y": 2
    },
    {
      "element": "SandStone",
      "mass": 100,
      "temperature": 265.13858,
      "location_x": -13,
      "location_y": 2
    },
    {
      "element": "Oxygen",
      "mass": 0.974942267,
      "temperature": 265.089111,
      "location_x": -12,
      "location_y": 2
    },
    {
      "element": "Oxygen",
      "mass": 0.998533726,
      "temperature": 265.021332,
      "location_x": -11,
      "location_y": 2
    },
    {
      "element": "Oxygen",
      "mass": 1.03969514,
      "temperature": 265.149994,
      "location_x": -10,
      "location_y": 2
    },
    {
      "element": "SandStone",
      "mass": 100,
      "temperature": 264.62854,
      "location_x": -9,
      "location_y": 2
    },
    {
      "element": "Wolframite",
      "mass": 575.950012,
      "temperature": 234.367523,
      "location_x": -8,
      "location_y": 2
    },
    {
      "element": "SandStone",
      "mass": 100,
      "temperature": 264.602539,
      "location_x": -7,
      "location_y": 2
    },
    {
      "element": "SandStone",
      "mass": 100,
      "temperature": 265.149994,
      "location_x": -6,
      "location_y": 2
    },
    {
      "element": "Oxygen",
      "mass": 0.985678434,
      "temperature": 265.120575,
      "location_x": -5,
      "location_y": 2
    },
    {
      "element": "Oxygen",
      "mass": 0.988438487,
      "temperature": 265.158203,
      "location_x": -4,
      "location_y": 2
    },
    {
      "element": "Oxygen",
      "mass": 0.996801019,
      "temperature": 265.164886,
      "location_x": -3,
      "location_y": 2
    },
    {
      "element": "Oxygen",
      "mass": 1.01182353,
      "temperature": 265.942108,
      "location_x": -2,
      "location_y": 2
    },
    {
      "element": "Oxygen",
      "mass": 1.04702497,
      "temperature": 266.688416,
      "location_x": -1,
      "location_y": 2
    },
    {
      "element": "Oxygen",
      "mass": 1.16186285,
      "temperature": 283.122803,
      "location_y": 2
    },
    {
      "element": "OxyRock",
      "mass": 198.23996,
      "temperature": 298.677216,
      "location_x": 1,
      "location_y": 2
    },
    {
      "element": "OxyRock",
      "mass": 199.679993,
      "temperature": 297.900726,
      "location_x": 2,
      "location_y": 2
    },
    {
      "element": "SandStone",
      "mass": 100,
      "temperature": 266.084198,
      "location_x": 3,
      "location_y": 2
    },
    {
      "element": "SandStone",
      "mass": 100,
      "temperature": 265.154388,
      "location_x": 4,
      "location_y": 2
    },
    {
      "element": "Snow",
      "mass": 10,
      "temperature": 259.149994,
      "location_x": 5,
      "location_y": 2
    },
    {
      "element": "SandStone",
      "mass": 100,
      "temperature": 265.149994,
      "location_x": 6,
      "location_y": 2
    },
    {
      "element": "SandStone",
      "mass": 100,
      "temperature": 265.149994,
      "location_x": 7,
      "location_y": 2
    },
    {
      "element": "SandStone",
      "mass": 100,
      "temperature": 265.149994,
      "location_x": 8,
      "location_y": 2
    },
    {
      "element": "Oxygen",
      "mass": 0.962810099,
      "temperature": 265.149994,
      "location_x": 9,
      "location_y": 2
    },
    {
      "element": "CarbonDioxide",
      "mass": 0.0996895954,
      "temperature": 265.149994,
      "location_x": 10,
      "location_y": 2
    },
    {
      "element": "Oxygen",
      "mass": 0.943355739,
      "temperature": 265.149994,
      "location_x": 11,
      "location_y": 2
    },
    {
      "element": "SandStone",
      "mass": 100,
      "temperature": 265.149994,
      "location_x": 12,
      "location_y": 2
    },
    {
      "element": "SandStone",
      "mass": 100,
      "temperature": 265.148743,
      "location_x": 13,
      "location_y": 2
    },
    {
      "element": "SandStone",
      "mass": 100,
      "temperature": 265.148956,
      "location_x": 14,
      "location_y": 2
    },
    {
      "element": "SandStone",
      "mass": 100,
      "temperature": 265.11145,
      "location_x": -13,
      "location_y": 3
    },
    {
      "element": "SandStone",
      "mass": 100,
      "temperature": 265.139893,
      "location_x": -12,
      "location_y": 3
    },
    {
      "element": "SandStone",
      "mass": 100,
      "temperature": 265.120483,
      "location_x": -11,
      "location_y": 3
    },
    {
      "element": "SandStone",
      "mass": 100,
      "temperature": 264.625885,
      "location_x": -10,
      "location_y": 3
    },
    {
      "element": "SandStone",
      "mass": 100,
      "temperature": 264.091675,
      "location_x": -9,
      "location_y": 3
    },
    {
      "element": "Wolframite",
      "mass": 575.950012,
      "temperature": 233.642944,
      "location_x": -8,
      "location_y": 3
    },
    {
      "element": "Snow",
      "mass": 10,
      "temperature": 259.149994,
      "location_x": -7,
      "location_y": 3
    },
    {
      "element": "SandStone",
      "mass": 100,
      "temperature": 265.124237,
      "location_x": -6,
      "location_y": 3
    },
    {
      "element": "SandStone",
      "mass": 100,
      "temperature": 265.143677,
      "location_x": -5,
      "location_y": 3
    },
    {
      "element": "SandStone",
      "mass": 100,
      "temperature": 265.149994,
      "location_x": -4,
      "location_y": 3
    },
    {
      "element": "SandStone",
      "mass": 100,
      "temperature": 265.149994,
      "location_x": -3,
      "location_y": 3
    },
    {
      "element": "SandStone",
      "mass": 100,
      "temperature": 265.150177,
      "location_x": -2,
      "location_y": 3
    },
    {
      "element": "SandStone",
      "mass": 100,
      "temperature": 265.153687,
      "location_x": -1,
      "location_y": 3
    },
    {
      "element": "SandStone",
      "mass": 100,
      "temperature": 265.222168,
      "location_y": 3
    },
    {
      "element": "SandStone",
      "mass": 100,
      "temperature": 265.568268,
      "location_x": 1,
      "location_y": 3
    },
    {
      "element": "SandStone",
      "mass": 100,
      "temperature": 265.561005,
      "location_x": 2,
      "location_y": 3
    },
    {
      "element": "SandStone",
      "mass": 100,
      "temperature": 265.138153,
      "location_x": 3,
      "location_y": 3
    },
    {
      "element": "CarbonDioxide",
      "mass": 0.299999803,
      "temperature": 263.849396,
      "location_x": 4,
      "location_y": 3
    },
    {
      "element": "Snow",
      "mass": 10,
      "temperature": 259.149994,
      "location_x": 5,
      "location_y": 3
    },
    {
      "element": "Snow",
      "mass": 10,
      "temperature": 259.149994,
      "location_x": 6,
      "location_y": 3
    },
    {
      "element": "Snow",
      "mass": 10,
      "temperature": 259.149994,
      "location_x": 7,
      "location_y": 3
    },
    {
      "element": "SandStone",
      "mass": 100,
      "temperature": 265.149994,
      "location_x": 8,
      "location_y": 3
    },
    {
      "element": "SandStone",
      "mass": 100,
      "temperature": 265.149994,
      "location_x": 9,
      "location_y": 3
    },
    {
      "element": "SandStone",
      "mass": 100,
      "temperature": 265.149994,
      "location_x": 10,
      "location_y": 3
    },
    {
      "element": "SandStone",
      "mass": 100,
      "temperature": 265.149994,
      "location_x": 11,
      "location_y": 3
    },
    {
      "element": "SandStone",
      "mass": 100,
      "temperature": 265.148743,
      "location_x": 12,
      "location_y": 3
    },
    {
      "element": "SedimentaryRock",
      "mass": 1840,
      "temperature": 250.149994,
      "location_x": 13,
      "location_y": 3
    },
    {
      "element": "SedimentaryRock",
      "mass": 1840,
      "temperature": 250.149994,
      "location_x": 14,
      "location_y": 3
    },
    {
      "element": "Snow",
      "mass": 10,
      "temperature": 259.149994,
      "location_x": -13,
      "location_y": 4
    },
    {
      "element": "Snow",
      "mass": 10,
      "temperature": 259.149994,
      "location_x": -12,
      "location_y": 4
    },
    {
      "element": "Snow",
      "mass": 10,
      "temperature": 259.149994,
      "location_x": -11,
      "location_y": 4
    },
    {
      "element": "Wolframite",
      "mass": 575.950012,
      "temperature": 233.924347,
      "location_x": -10,
      "location_y": 4
    },
    {
      "element": "Wolframite",
      "mass": 575.950012,
      "temperature": 233.268402,
      "location_x": -9,
      "location_y": 4
    },
    {
      "element": "Wolframite",
      "mass": 575.950012,
      "temperature": 232.839951,
      "location_x": -8,
      "location_y": 4
    },
    {
      "element": "Snow",
      "mass": 10,
      "temperature": 259.149994,
      "location_x": -7,
      "location_y": 4
    },
    {
      "element": "Snow",
      "mass": 10,
      "temperature": 259.149994,
      "location_x": -6,
      "location_y": 4
    },
    {
      "element": "Snow",
      "mass": 10,
      "temperature": 259.149994,
      "location_x": -5,
      "location_y": 4
    },
    {
      "element": "Snow",
      "mass": 10,
      "temperature": 259.149994,
      "location_x": -4,
      "location_y": 4
    },
    {
      "element": "Snow",
      "mass": 10,
      "temperature": 259.149994,
      "location_x": -3,
      "location_y": 4
    },
    {
      "element": "CarbonDioxide",
      "mass": 0.985666275,
      "temperature": 265.149994,
      "location_x": -2,
      "location_y": 4
    },
    {
      "element": "CarbonDioxide",
      "mass": 0.980705082,
      "temperature": 264.770538,
      "location_x": -1,
      "location_y": 4
    },
    {
      "element": "CarbonDioxide",
      "mass": 0.972210228,
      "temperature": 265.951721,
      "location_y": 4
    },
    {
      "element": "CarbonDioxide",
      "mass": 0.971047342,
      "temperature": 265.235199,
      "location_x": 1,
      "location_y": 4
    },
    {
      "element": "CarbonDioxide",
      "mass": 0.952982128,
      "temperature": 265.84259,
      "location_x": 2,
      "location_y": 4
    },
    {
      "element": "CarbonDioxide",
      "mass": 0.925173342,
      "temperature": 253.074188,
      "location_x": 3,
      "location_y": 4
    },
    {
      "element": "SedimentaryRock",
      "mass": 1840,
      "temperature": 255.085632,
      "location_x": 4,
      "location_y": 4
    },
    {
      "element": "Snow",
      "mass": 10,
      "temperature": 259.149994,
      "location_x": 5,
      "location_y": 4
    },
    {
      "element": "CarbonDioxide",
      "mass": 1.15832341,
      "temperature": 265.149994,
      "location_x": 6,
      "location_y": 4
    },
    {
      "element": "CarbonDioxide",
      "mass": 1.16081762,
      "temperature": 265.125549,
      "location_x": 7,
      "location_y": 4
    },
    {
      "element": "Snow",
      "mass": 10,
      "temperature": 259.149994,
      "location_x": 8,
      "location_y": 4
    },
    {
      "element": "CarbonDioxide",
      "mass": 0.962691247,
      "temperature": 265.143402,
      "location_x": 9,
      "location_y": 4
    },
    {
      "element": "CarbonDioxide",
      "mass": 0.960895061,
      "temperature": 265.147186,
      "location_x": 10,
      "location_y": 4
    },
    {
      "element": "CarbonDioxide",
      "mass": 0.969109118,
      "temperature": 264.316528,
      "location_x": 11,
      "location_y": 4
    },
    {
      "element": "CarbonDioxide",
      "mass": 0.970358849,
      "temperature": 264.177734,
      "location_x": 12,
      "location_y": 4
    },
    {
      "element": "SedimentaryRock",
      "mass": 1840,
      "temperature": 250.149994,
      "location_x": 13,
      "location_y": 4
    },
    {
      "element": "SedimentaryRock",
      "mass": 1840,
      "temperature": 250.149994,
      "location_x": 14,
      "location_y": 4
    },
    {
      "element": "Snow",
      "mass": 10,
      "temperature": 259.149994,
      "location_x": -10,
      "location_y": 5
    },
    {
      "element": "Wolframite",
      "mass": 575.950012,
      "temperature": 232.89917,
      "location_x": -9,
      "location_y": 5
    },
    {
      "element": "Snow",
      "mass": 10,
      "temperature": 259.149994,
      "location_x": -8,
      "location_y": 5
    },
    {
      "element": "Snow",
      "mass": 10,
      "temperature": 259.149994,
      "location_x": -7,
      "location_y": 5
    },
    {
      "element": "Snow",
      "mass": 10,
      "temperature": 259.149994,
      "location_x": -6,
      "location_y": 5
    },
    {
      "element": "CarbonDioxide",
      "mass": 0.951390624,
      "temperature": 261.806091,
      "location_x": -5,
      "location_y": 5
    },
    {
      "element": "CarbonDioxide",
      "mass": 0.954559028,
      "temperature": 264.912079,
      "location_x": -4,
      "location_y": 5
    },
    {
      "element": "CarbonDioxide",
      "mass": 0.97086364,
      "temperature": 264.911499,
      "location_x": -3,
      "location_y": 5
    },
    {
      "element": "CarbonDioxide",
      "mass": 0.973740399,
      "temperature": 264.84668,
      "location_x": -2,
      "location_y": 5
    },
    {
      "element": "CarbonDioxide",
      "mass": 0.978808701,
      "temperature": 264.994141,
      "location_x": -1,
      "location_y": 5
    },
    {
      "element": "CarbonDioxide",
      "mass": 0.97683543,
      "temperature": 262.212646,
      "location_y": 5
    },
    {
      "element": "CarbonDioxide",
      "mass": 0.968770504,
      "temperature": 256.824982,
      "location_x": 1,
      "location_y": 5
    },
    {
      "element": "CarbonDioxide",
      "mass": 0.962535739,
      "temperature": 240.433456,
      "location_x": 2,
      "location_y": 5
    },
    {
      "element": "Wolframite",
      "mass": 575.950012,
      "temperature": 232.424545,
      "location_x": 3,
      "location_y": 5
    },
    {
      "element": "Wolframite",
      "mass": 575.950012,
      "temperature": 232.342438,
      "location_x": 4,
      "location_y": 5
    },
    {
      "element": "CarbonDioxide",
      "mass": 1.14226389,
      "temperature": 244.639771,
      "location_x": 5,
      "location_y": 5
    },
    {
      "element": "CarbonDioxide",
      "mass": 1.1477797,
      "temperature": 251.130798,
      "location_x": 6,
      "location_y": 5
    },
    {
      "element": "CarbonDioxide",
      "mass": 1.11742985,
      "temperature": 264.725983,
      "location_x": 7,
      "location_y": 5
    },
    {
      "element": "CarbonDioxide",
      "mass": 1.01803064,
      "temperature": 265.145538,
      "location_x": 8,
      "location_y": 5
    },
    {
      "element": "CarbonDioxide",
      "mass": 0.968557,
      "temperature": 264.827942,
      "location_x": 9,
      "location_y": 5
    },
    {
      "element": "CarbonDioxide",
      "mass": 0.963628352,
      "temperature": 263.977112,
      "location_x": 10,
      "location_y": 5
    },
    {
      "element": "CarbonDioxide",
      "mass": 0.972141743,
      "temperature": 264.493378,
      "location_x": 11,
      "location_y": 5
    },
    {
      "element": "CarbonDioxide",
      "mass": 0.973082125,
      "temperature": 243.572586,
      "location_x": 12,
      "location_y": 5
    },
    {
      "element": "Ice",
      "mass": 980,
      "temperature": 254.149994,
      "location_x": 13,
      "location_y": 5
    },
    {
      "element": "CarbonDioxide",
      "mass": 0.00162635045,
      "temperature": 248.202179,
      "location_x": 14,
      "location_y": 5
    },
    {
      "element": "Ice",
      "mass": 980,
      "temperature": 254.149994,
      "location_x": -8,
      "location_y": 6
    },
    {
      "element": "Ice",
      "mass": 980,
      "temperature": 254.149994,
      "location_x": -7,
      "location_y": 6
    },
    {
      "element": "Ice",
      "mass": 980,
      "temperature": 254.149994,
      "location_x": -6,
      "location_y": 6
    },
    {
      "element": "Ice",
      "mass": 980,
      "temperature": 254.149994,
      "location_x": -5,
      "location_y": 6
    },
    {
      "element": "CarbonDioxide",
      "mass": 0.963267922,
      "temperature": 253.889404,
      "location_x": -4,
      "location_y": 6
    },
    {
      "element": "CarbonDioxide",
      "mass": 0.974871814,
      "temperature": 249.193176,
      "location_x": -3,
      "location_y": 6
    },
    {
      "element": "CarbonDioxide",
      "mass": 0.951526463,
      "temperature": 256.860352,
      "location_x": -2,
      "location_y": 6
    },
    {
      "element": "CarbonDioxide",
      "mass": 0.980618656,
      "temperature": 248.584229,
      "location_x": -1,
      "location_y": 6
    },
    {
      "element": "SedimentaryRock",
      "mass": 1840,
      "temperature": 250.149994,
      "location_y": 6
    },
    {
      "element": "Ice",
      "mass": 980,
      "temperature": 254.149994,
      "location_x": 1,
      "location_y": 6
    },
    {
      "element": "Wolframite",
      "mass": 575.950012,
      "temperature": 232.542435,
      "location_x": 2,
      "location_y": 6
    },
    {
      "element": "Wolframite",
      "mass": 575.950012,
      "temperature": 232.149994,
      "location_x": 3,
      "location_y": 6
    },
    {
      "element": "Wolframite",
      "mass": 575.950012,
      "temperature": 232.149994,
      "location_x": 4,
      "location_y": 6
    },
    {
      "element": "Wolframite",
      "mass": 575.950012,
      "temperature": 232.354355,
      "location_x": 5,
      "location_y": 6
    },
    {
      "element": "Wolframite",
      "mass": 575.950012,
      "temperature": 234.734558,
      "location_x": 6,
      "location_y": 6
    },
    {
      "element": "Wolframite",
      "mass": 525.950012,
      "temperature": 262.471466,
      "location_x": 7,
      "location_y": 6
    },
    {
      "element": "Ice",
      "mass": 980,
      "temperature": 254.149994,
      "location_x": 8,
      "location_y": 6
    },
    {
      "element": "SedimentaryRock",
      "mass": 1840,
      "temperature": 250.149994,
      "location_x": 9,
      "location_y": 6
    },
    {
      "element": "SedimentaryRock",
      "mass": 1840,
      "temperature": 250.149994,
      "location_x": 10,
      "location_y": 6
    },
    {
      "element": "CarbonDioxide",
      "mass": 0.984807491,
      "temperature": 248.585129,
      "location_x": 11,
      "location_y": 6
    },
    {
      "element": "Ice",
      "mass": 980,
      "temperature": 254.149994,
      "location_x": 12,
      "location_y": 6
    },
    {
      "element": "Ice",
      "mass": 980,
      "temperature": 254.149994,
      "location_x": 13,
      "location_y": 6
    },
    {
      "element": "Snow",
      "mass": 10,
      "temperature": 259.149994,
      "location_x": -6,
      "location_y": 7
    },
    {
      "element": "Ice",
      "mass": 980,
      "temperature": 254.149994,
      "location_x": -5,
      "location_y": 7
    },
    {
      "element": "Ice",
      "mass": 980,
      "temperature": 254.149994,
      "location_x": -4,
      "location_y": 7
    },
    {
      "element": "Ice",
      "mass": 980,
      "temperature": 254.149994,
      "location_x": -3,
      "location_y": 7
    },
    {
      "element": "Ice",
      "mass": 980,
      "temperature": 254.149994,
      "location_x": -2,
      "location_y": 7
    },
    {
      "element": "Ice",
      "mass": 980,
      "temperature": 254.149994,
      "location_x": -1,
      "location_y": 7
    },
    {
      "element": "Ice",
      "mass": 980,
      "temperature": 254.149994,
      "location_y": 7
    },
    {
      "element": "Ice",
      "mass": 980,
      "temperature": 254.149994,
      "location_x": 1,
      "location_y": 7
    },
    {
      "element": "SedimentaryRock",
      "mass": 1840,
      "temperature": 250.149994,
      "location_x": 10,
      "location_y": 7
    },
    {
      "element": "SedimentaryRock",
      "mass": 1840,
      "temperature": 250.149994,
      "location_x": 11,
      "location_y": 7
    },
    {
      "element": "SedimentaryRock",
      "mass": 1840,
      "temperature": 250.149994,
      "location_x": 12,
      "location_y": 7
    },
    {
      "element": "Oxygen",
      "mass": 0.451432139,
      "temperature": 240.608246,
      "location_x": -14,
      "location_y": -5
    },
    {
      "element": "Oxygen",
      "mass": 0.690107882,
      "temperature": 263.063782,
      "location_x": -13,
      "location_y": -5
    },
    {
      "element": "Oxygen",
      "mass": 0.366114736,
      "temperature": 254.640732,
      "location_x": -14,
      "location_y": -4
    },
    {
      "element": "Oxygen",
      "mass": 0.491716415,
      "temperature": 257.976196,
      "location_x": -12,
      "location_y": -6
    },
    {
      "element": "Oxygen",
      "mass": 0.555598974,
      "temperature": 260.892151,
      "location_x": -11,
      "location_y": -6
    },
    {
      "element": "Oxygen",
      "mass": 0.311286598,
      "temperature": 234.316757,
      "location_x": -14,
      "location_y": -6
    },
    {
      "element": "Oxygen",
      "mass": 0.480181724,
      "temperature": 240.300903,
      "location_x": -13,
      "location_y": -6
    },
    {
      "element": "Oxygen",
      "mass": 0.128926069,
      "temperature": 253.270401,
      "location_x": -14,
      "location_y": -3
    },
    {
      "element": "Oxygen",
      "mass": 0.163703412,
      "temperature": 242.990952,
      "location_x": -14,
      "location_y": -2
    },
    {
      "element": "Oxygen",
      "mass": 0.569131851,
      "temperature": 239.437561,
      "location_x": -14,
      "location_y": -1
    },
    {
      "element": "Oxygen",
      "mass": 0.83655417,
      "temperature": 239.71228,
      "location_x": -14
    },
    {
      "element": "Oxygen",
      "mass": 0.71053344,
      "temperature": 255.960571,
      "location_x": -14,
      "location_y": 1
    },
    {
      "element": "Ice",
      "mass": 980,
      "temperature": 254.149994,
      "location_x": 15,
      "location_y": 1
    },
    {
      "element": "Ice",
      "mass": 980,
      "temperature": 254.149994,
      "location_x": 15,
      "location_y": 2
    },
    {
      "element": "CarbonDioxide",
      "mass": 0.265374452,
      "temperature": 260.922455,
      "location_x": 16
    },
    {
      "element": "CarbonDioxide",
      "mass": 0.132962868,
      "temperature": 256.242828,
      "location_x": 16,
      "location_y": 1
    },
    {
      "element": "CarbonDioxide",
      "mass": 0.0430510156,
      "temperature": 254.360779,
      "location_x": 16,
      "location_y": 2
    },
    {
      "element": "CarbonDioxide",
      "mass": 0.00984166097,
      "temperature": 256.363525,
      "location_x": 15,
      "location_y": 3
    },
    {
      "element": "CarbonDioxide",
      "mass": 0.0113961911,
      "temperature": 249.813812,
      "location_x": 16,
      "location_y": 3
    },
    {
      "element": "CarbonDioxide",
      "mass": 0.00629138015,
      "temperature": 254.640747,
      "location_x": 15,
      "location_y": 4
    },
    {
      "element": "CarbonDioxide",
      "mass": 0.00172277028,
      "temperature": 248.494614,
      "location_x": 15,
      "location_y": 5
    },
    {
      "element": "Dirt",
      "mass": 1840,
      "temperature": 258.149994,
      "location_x": 15,
      "location_y": -5
    },
    {
      "element": "Dirt",
      "mass": 1840,
      "temperature": 258.149994,
      "location_x": 16,
      "location_y": -5
    },
    {
      "element": "Dirt",
      "mass": 1840,
      "temperature": 258.149994,
      "location_x": 14,
      "location_y": -6
    },
    {
      "element": "Dirt",
      "mass": 1840,
      "temperature": 258.149994,
      "location_x": 15,
      "location_y": -6
    },
    {
      "element": "SedimentaryRock",
      "mass": 1840,
      "temperature": 250.149994,
      "location_x": 13,
      "location_y": -6
    },
    {
      "element": "CarbonDioxide",
      "mass": 0.703128457,
      "temperature": 257.337189,
      "location_x": -11,
      "location_y": 5
    },
    {
      "element": "CarbonDioxide",
      "mass": 0.11180488,
      "temperature": 257.337189,
      "location_x": -11,
      "location_y": 6
    },
    {
      "element": "Oxygen",
      "mass": 0.688440144,
      "temperature": 243.204376,
      "location_x": -10,
      "location_y": 6
    },
    {
      "element": "Oxygen",
      "mass": 0.756667435,
      "temperature": 250.558228,
      "location_x": -9,
      "location_y": 6
    },
    {
      "element": "Oxygen",
      "mass": 0.478483856,
      "temperature": 236.913391,
      "location_x": -10,
      "location_y": 7
    },
    {
      "element": "Oxygen",
      "mass": 0.556766331,
      "temperature": 259.797729,
      "location_x": -9,
      "location_y": 7
    },
    {
      "element": "Oxygen",
      "mass": 0.462107956,
      "temperature": 257.199371,
      "location_x": -8,
      "location_y": 7
    }
  ],
  "buildings": [
    {
      "id": "TilePOI",
      "location_x": 13,
      "location_y": -4,
      "element": "SandStone",
      "temperature": 265.133606
    },
    {
      "id": "TilePOI",
      "location_x": 12,
      "location_y": -4,
      "element": "SandStone",
      "temperature": 265.131042
    },
    {
      "id": "TilePOI",
      "location_x": 11,
      "location_y": -4,
      "element": "SandStone",
      "temperature": 265.146301
    },
    {
      "id": "TilePOI",
      "location_x": 10,
      "location_y": -4,
      "element": "SandStone",
      "temperature": 265.149994
    },
    {
      "id": "TilePOI",
      "location_x": 9,
      "location_y": -4,
      "element": "SandStone",
      "temperature": 265.149994
    },
    {
      "id": "TilePOI",
      "location_x": 8,
      "location_y": -4,
      "element": "SandStone",
      "temperature": 265.148529
    },
    {
      "id": "TilePOI",
      "location_x": 7,
      "location_y": -4,
      "element": "SandStone",
      "temperature": 265.145599
    },
    {
      "id": "TilePOI",
      "location_x": 6,
      "location_y": -4,
      "element": "SandStone",
      "temperature": 265.148315
    },
    {
      "id": "TilePOI",
      "location_x": 5,
      "location_y": -4,
      "element": "SandStone",
      "temperature": 265.148102
    },
    {
      "id": "TilePOI",
      "location_x": 4,
      "location_y": -4,
      "element": "SandStone",
      "temperature": 265.148254
    },
    {
      "id": "TilePOI",
      "location_x": 3,
      "location_y": -4,
      "element": "SandStone",
      "temperature": 265.147003
    },
    {
      "id": "TilePOI",
      "location_x": 2,
      "location_y": -4,
      "element": "SandStone",
      "temperature": 265.164734
    },
    {
      "id": "TilePOI",
      "location_x": 1,
      "location_y": -4,
      "element": "SandStone",
      "temperature": 265.136719
    },
    {
      "id": "TilePOI",
      "location_y": -4,
      "element": "SandStone",
      "temperature": 265.138672
    },
    {
      "id": "TilePOI",
      "location_x": -1,
      "location_y": -4,
      "element": "SandStone",
      "temperature": 265.140228
    },
    {
      "id": "TilePOI",
      "location_x": -2,
      "location_y": -4,
      "element": "SandStone",
      "temperature": 265.147491
    },
    {
      "id": "TilePOI",
      "location_x": -3,
      "location_y": -4,
      "element": "SandStone",
      "temperature": 265.147614
    },
    {
      "id": "TilePOI",
      "location_x": -4,
      "location_y": -4,
      "element": "SandStone",
      "temperature": 265.141571
    },
    {
      "id": "TilePOI",
      "location_x": -5,
      "location_y": -4,
      "element": "SandStone",
      "temperature": 265.144958
    },
    {
      "id": "TilePOI",
      "location_x": -6,
      "location_y": -4,
      "element": "SandStone",
      "temperature": 265.129486
    },
    {
      "id": "TilePOI",
      "location_x": -8,
      "location_y": -4,
      "element": "SandStone",
      "temperature": 265.122864
    },
    {
      "id": "TilePOI",
      "location_x": 14,
      "element": "SandStone",
      "temperature": 265.149353
    },
    {
      "id": "TilePOI",
      "location_x": 14,
      "location_y": 1,
      "element": "SandStone",
      "temperature": 265.149902
    },
    {
      "id": "TilePOI",
      "location_x": 14,
      "location_y": 2,
      "element": "SandStone",
      "temperature": 265.149902
    },
    {
      "id": "TilePOI",
      "location_x": 13,
      "location_y": 2,
      "element": "SandStone",
      "temperature": 265.149963
    },
    {
      "id": "TilePOI",
      "location_x": 12,
      "location_y": 2,
      "element": "SandStone",
      "temperature": 265.149994
    },
    {
      "id": "TilePOI",
      "location_x": 12,
      "location_y": 3,
      "element": "SandStone",
      "temperature": 265.149963
    },
    {
      "id": "TilePOI",
      "location_x": 11,
      "location_y": 3,
      "element": "SandStone",
      "temperature": 265.149994
    },
    {
      "id": "TilePOI",
      "location_x": 10,
      "location_y": 3,
      "element": "SandStone",
      "temperature": 265.149994
    },
    {
      "id": "TilePOI",
      "location_x": 9,
      "location_y": 3,
      "element": "SandStone",
      "temperature": 265.149994
    },
    {
      "id": "TilePOI",
      "location_x": 8,
      "location_y": 3,
      "element": "SandStone",
      "temperature": 265.149994
    },
    {
      "id": "TilePOI",
      "location_x": 8,
      "location_y": 2,
      "element": "SandStone",
      "temperature": 265.149994
    },
    {
      "id": "TilePOI",
      "location_x": 7,
      "location_y": 2,
      "element": "SandStone",
      "temperature": 265.149994
    },
    {
      "id": "TilePOI",
      "location_x": 6,
      "location_y": 2,
      "element": "SandStone",
      "temperature": 265.149994
    },
    {
      "id": "TilePOI",
      "location_x": 6,
      "location_y": 1,
      "element": "SandStone",
      "temperature": 265.149994
    },
    {
      "id": "TilePOI",
      "location_x": 6,
      "element": "SandStone",
      "temperature": 265.149994
    },
    {
      "id": "TilePOI",
      "location_x": 5,
      "element": "SandStone",
      "temperature": 265.149994
    },
    {
      "id": "TilePOI",
      "location_x": 4,
      "element": "SandStone",
      "temperature": 265.157867
    },
    {
      "id": "TilePOI",
      "location_x": 4,
      "location_y": 1,
      "element": "SandStone",
      "temperature": 265.192993
    },
    {
      "id": "PropGravitasLabWall",
      "location_x": -6,
      "element": "Granite",
      "temperature": 265.152069
    },
    {
      "id": "TilePOI",
      "location_x": 2,
      "location_y": 3,
      "element": "SandStone",
      "temperature": 265.283173
    },
    {
      "id": "TilePOI",
      "location_x": 1,
      "location_y": 3,
      "element": "SandStone",
      "temperature": 265.284363
    },
    {
      "id": "TilePOI",
      "location_y": 3,
      "element": "SandStone",
      "temperature": 265.158478
    },
    {
      "id": "TilePOI",
      "location_x": -1,
      "location_y": 3,
      "element": "SandStone",
      "temperature": 265.150085
    },
    {
      "id": "TilePOI",
      "location_x": -2,
      "location_y": 3,
      "element": "SandStone",
      "temperature": 265.150177
    },
    {
      "id": "TilePOI",
      "location_x": -3,
      "location_y": 3,
      "element": "SandStone",
      "temperature": 265.149994
    },
    {
      "id": "TilePOI",
      "location_x": -4,
      "location_y": 3,
      "element": "SandStone",
      "temperature": 265.149994
    },
    {
      "id": "TilePOI",
      "location_x": -8,
      "element": "SandStone",
      "temperature": 265.149994
    },
    {
      "id": "TilePOI",
      "location_x": -9,
      "element": "SandStone",
      "temperature": 265.149994
    },
    {
      "id": "TilePOI",
      "location_x": -7,
      "element": "SandStone",
      "temperature": 265.149994
    },
    {
      "id": "TilePOI",
      "location_x": -7,
      "location_y": 1,
      "element": "SandStone",
      "temperature": 265.149994
    },
    {
      "id": "TilePOI",
      "location_x": -7,
      "location_y": 2,
      "element": "SandStone",
      "temperature": 265.149994
    },
    {
      "id": "TilePOI",
      "location_x": -6,
      "location_y": 2,
      "element": "SandStone",
      "temperature": 265.149994
    },
    {
      "id": "TilePOI",
      "location_x": -6,
      "location_y": 3,
      "element": "SandStone",
      "temperature": 265.149994
    },
    {
      "id": "TilePOI",
      "location_x": -5,
      "location_y": 3,
      "element": "SandStone",
      "temperature": 265.147003
    },
    {
      "id": "TilePOI",
      "location_x": -9,
      "location_y": 1,
      "element": "SandStone",
      "temperature": 265.149994
    },
    {
      "id": "TilePOI",
      "location_x": -9,
      "location_y": 2,
      "element": "SandStone",
      "temperature": 265.149994
    },
    {
      "id": "TilePOI",
      "location_x": -9,
      "location_y": 3,
      "element": "SandStone",
      "temperature": 265.149994
    },
    {
      "id": "TilePOI",
      "location_x": -10,
      "location_y": 3,
      "element": "SandStone",
      "temperature": 265.149994
    },
    {
      "id": "TilePOI",
      "location_x": -11,
      "location_y": 3,
      "element": "SandStone",
      "temperature": 265.149231
    },
    {
      "id": "TilePOI",
      "location_x": -12,
      "location_y": 3,
      "element": "SandStone",
      "temperature": 265.148743
    },
    {
      "id": "TilePOI",
      "location_x": -13,
      "location_y": -4,
      "element": "SandStone",
      "temperature": 265.013062
    },
    {
      "id": "TilePOI",
      "location_x": -12,
      "location_y": -4,
      "element": "SandStone",
      "temperature": 265.13913
    },
    {
      "id": "TilePOI",
      "location_x": -13,
      "location_y": 3,
      "element": "SandStone",
      "temperature": 265.129089
    },
    {
      "id": "TilePOI",
      "location_x": -13,
      "location_y": 2,
      "element": "SandStone",
      "temperature": 265.141785
    },
    {
      "id": "TilePOI",
      "location_x": -14,
      "location_y": 2,
      "element": "SandStone",
      "temperature": 264.960388
    },
    {
      "id": "TilePOI",
      "location_x": -10,
      "location_y": -4,
      "element": "SandStone",
      "temperature": 265.138031
    },
    {
      "id": "RationBox",
      "location_x": 2,
      "location_y": -3,
      "element": "SandStone",
      "temperature": 265.151031,
      "storage": [
        {
          "id": "FieldRation",
          "element": "Creature",
          "units": 17,
          "temperature": 292.91391,
          "rottable": {}
        }
      ]
    },
    {
      "id": "PropGravitasLabWall",
      "location_x": 12,
      "location_y": -3,
      "element": "Granite",
      "temperature": 265.149628
    },
    {
      "id": "PropGravitasLabWall",
      "location_x": 10,
      "location_y": -3,
      "element": "Granite",
      "temperature": 265.148499
    },
    {
      "id": "PropGravitasLabWall",
      "location_x": 8,
      "location_y": -3,
      "element": "Granite",
      "temperature": 265.150055
    },
    {
      "id": "PropGravitasLabWall",
      "location_x": 6,
      "location_y": -3,
      "element": "Granite",
      "temperature": 265.156982
    },
    {
      "id": "PropGravitasLabWall",
      "location_x": 3,
      "location_y": -3,
      "element": "Granite",
      "temperature": 265.198486
    },
    {
      "id": "PropGravitasLabWall",
      "location_x": 1,
      "location_y": -3,
      "element": "Granite",
      "temperature": 265.217926
    },
    {
      "id": "PropGravitasLabWall",
      "location_x": -1,
      "location_y": -3,
      "element": "Granite",
      "temperature": 265.164581
    },
    {
      "id": "PropGravitasLabWall",
      "location_x": -3,
      "location_y": -3,
      "element": "Granite",
      "temperature": 265.150177
    },
    {
      "id": "PropGravitasLabWall",
      "location_x": -5,
      "location_y": -3,
      "element": "Granite",
      "temperature": 265.149994
    },
    {
      "id": "PropGravitasLabWall",
      "location_x": -7,
      "location_y": -3,
      "element": "Granite",
      "temperature": 265.149445
    },
    {
      "id": "PropGravitasLabWall",
      "location_x": -10,
      "location_y": -3,
      "element": "Granite",
      "temperature": 265.138763
    },
    {
      "id": "GravitasDoor",
      "location_x": -8,
      "location_y": -3,
      "element": "Cuprite",
      "temperature": 265.149567
    },
    {
      "id": "PropGravitasLabWall",
      "location_x": 2,
      "element": "Granite",
      "temperature": 290.516052
    },
    {
      "id": "TilePOI",
      "location_x": 3,
      "location_y": 3,
      "element": "SandStone",
      "temperature": 265.157227
    },
    {
      "id": "TilePOI",
      "location_x": 4,
      "location_y": 2,
      "element": "SandStone",
      "temperature": 265.154388
    },
    {
      "id": "TilePOI",
      "location_x": 3,
      "location_y": 2,
      "element": "SandStone",
      "temperature": 265.328674
    },
    {
      "id": "PropGravitasWall",
      "location_x": 7,
      "location_y": 1,
      "element": "Granite",
      "temperature": 265.149994
    },
    {
      "id": "PropGravitasWall",
      "location_x": 7,
      "element": "Granite",
      "temperature": 265.149994
    },
    {
      "id": "PropGravitasWall",
      "location_x": 8,
      "element": "Granite",
      "temperature": 265.149994
    },
    {
      "id": "PropGravitasWall",
      "location_x": 8,
      "location_y": 1,
      "element": "Granite",
      "temperature": 265.149994
    },
    {
      "id": "PropGravitasWall",
      "location_x": 9,
      "element": "Granite",
      "temperature": 265.149994
    },
    {
      "id": "PropGravitasWall",
      "location_x": 10,
      "element": "Granite",
      "temperature": 265.149994
    },
    {
      "id": "PropGravitasWall",
      "location_x": 11,
      "element": "Granite",
      "temperature": 265.149994
    },
    {
      "id": "PropGravitasWall",
      "location_x": 12,
      "element": "Granite",
      "temperature": 265.149994
    },
    {
      "id": "PropGravitasWall",
      "location_x": 12,
      "location_y": 1,
      "element": "Granite",
      "temperature": 265.149994
    },
    {
      "id": "PropGravitasWall",
      "location_x": 13,
      "location_y": 1,
      "element": "Granite",
      "temperature": 265.149994
    },
    {
      "id": "PropGravitasWall",
      "location_x": 13,
      "element": "Granite",
      "temperature": 265.149994
    },
    {
      "id": "PropGravitasWall",
      "location_x": -12,
      "location_y": 2,
      "element": "Granite",
      "temperature": 265.147888
    },
    {
      "id": "PropGravitasWall",
      "location_x": -12,
      "location_y": 1,
      "element": "Granite",
      "temperature": 265.034882
    },
    {
      "id": "GravitasDoor",
      "location_x": 5,
      "location_y": -3,
      "element": "Cuprite",
      "temperature": 265.151062
    },
    {
      "id": "GravitasDoor",
      "location_x": 14,
      "location_y": -3,
      "element": "Cuprite",
      "temperature": 265.113983
    },
    {
      "id": "PropGravitasLabWindowHorizontal",
      "location_x": 10,
      "location_y": 1,
      "element": "Glass",
      "temperature": 265.149994
    },
    {
      "id": "PropGravitasLabWindow",
      "location_x": -11,
      "element": "Glass",
      "temperature": 265.145996
    },
    {
      "id": "PropGravitasLabWindow",
      "location_x": -4,
      "element": "Glass",
      "temperature": 265.152161
    },
    {
      "id": "PropGravitasLabWindow",
      "location_x": -2,
      "element": "Glass",
      "temperature": 265.217468
    },
    {
      "id": "PropGravitasLabWindow",
      "element": "Glass",
      "temperature": 285.842987
    }
  ],
  "otherEntities": [
    {
      "id": "PropGravitasJar1",
      "location_x": 7,
      "location_y": -3,
      "element": "Granite",
      "temperature": 294.149994,
      "units": 1,
      "type": "Other"
    },
    {
      "id": "PropGravitasJar2",
      "location_x": -6,
      "location_y": -3,
      "element": "Granite",
      "temperature": 294.149994,
      "units": 1,
      "type": "Other"
    },
    {
      "id": "PropGravitasShelf",
      "location_x": -5,
      "element": "Granite",
      "temperature": 294.149994,
      "units": 1,
      "type": "Other"
    },
    {
      "id": "WarpReceiver",
      "location_x": 10,
      "location_y": -3,
      "element": "Unobtanium",
      "temperature": 294.149994,
      "units": 1,
      "type": "Other"
    },
    {
      "id": "WarpPortal",
      "location_x": -12,
      "location_y": -3,
      "element": "Unobtanium",
      "temperature": 294.149994,
      "units": 1,
      "type": "Other"
    },
    {
      "id": "CryoTank",
      "location_x": -3,
      "location_y": -3,
      "element": "Unobtanium",
      "temperature": 294.149994,
      "units": 1,
      "type": "Other"
    },
    {
      "id": "PropClock",
      "location_x": 2,
      "element": "Unobtanium",
      "temperature": 294.149994,
      "units": 1,
      "type": "Other"
    }
  ]
}
